gauthuserinfo/__init__.py
gauthuserinfo/gauthuserinfo.py
gauthuserinfo-1.0.0.dist-info/METADATA
gauthuserinfo-1.0.0.dist-info/WHEEL
gauthuserinfo-1.0.0.dist-info/entry_points.txt
gauthuserinfo-1.0.0.dist-info/top_level.txt
gauthuserinfo-1.0.0.dist-info/RECORD
