Metadata-Version: 2.1
Name: gauthuserinfo
Version: 1.0.0
Requires-Dist: requests
